{"_ts":[1493663727],"_r":{"breakdown":{"html":{"bytes":[56622],"requests":[8]},"js":{"bytes":[557201],"requests":[57]},"css":{"bytes":[212114],"requests":[14]},"image":{"bytes":[1294782],"requests":[87]},"flash":{"bytes":[0],"requests":[0]},"font":{"bytes":[50549],"requests":[4]},"other":{"bytes":[461],"requests":[1]}},"date":[1493663727],"domElements":[2233],"domInteractive":[2901],"firstPaint":[1943],"fullyLoaded":[7192],"id":["170501_G4_11A6"],"loadTime":[6495],"render":[2574],"SpeedIndex":[4581],"TTFB":[640],"videoFrames":[[{"_i":"frame_0000.jpg","_t":0,"_vc":0},{"_i":"frame_0026.jpg","_t":2600,"_vc":0},{"_i":"frame_0030.jpg","_t":3000,"_vc":0},{"_i":"frame_0042.jpg","_t":4200,"_vc":1},{"_i":"frame_0045.jpg","_t":4500,"_vc":77},{"_i":"frame_0047.jpg","_t":4700,"_vc":81},{"_i":"frame_0049.jpg","_t":4900,"_vc":100}]],"visualComplete":[4900],"lighthouse":[null],"pagespeed":[85]}}